{
 "mid": {
  "winrate": 46.1,
  "games": 11000,
  "crashed": 0,
  "violations": [],
  "avgRounds": 9.4,
  "winTypes": {
   "ko": 2339,
   "bell": 2491,
   "sudden": 245,
   "alt": 0
  },
  "shattersPerGame": 0.8,
  "mirrorsPerGame": 0.002,
  "blizzPerGame": 0,
  "icel": {
   "bornPerGame": 0.303,
   "removalShare": {
    "spent": 2.9,
    "countered": 0.7,
    "zonelost": 96.4
   },
   "avgLifespanRounds": 1.93,
   "survivorsPerGame": 0.25
  },
  "maxLine": {
   "corePerGame": 0.0007,
   "withFlowPerGame": 0.0002
  },
  "matchups": {
   "G": 46.1,
   "M": 52.3,
   "C": 40.8,
   "K": 38.5,
   "Z": 72,
   "L": 38.2,
   "D": 32.8,
   "Y": 43.2,
   "W": 57.8,
   "X": 32,
   "O": 53.8
  }
 },
 "max": {
  "winrate": 45.8,
  "games": 11000,
  "crashed": 0,
  "violations": [],
  "avgRounds": 9.48,
  "winTypes": {
   "ko": 2019,
   "bell": 2731,
   "sudden": 287,
   "alt": 0
  },
  "shattersPerGame": 0.58,
  "mirrorsPerGame": 0,
  "blizzPerGame": 0.18,
  "icel": {
   "bornPerGame": 0,
   "removalShare": null,
   "avgLifespanRounds": null,
   "survivorsPerGame": 0
  },
  "maxLine": {
   "corePerGame": 0,
   "withFlowPerGame": 0
  },
  "matchups": {
   "G": 46.1,
   "M": 58.4,
   "C": 38.6,
   "K": 38.4,
   "Z": 70.9,
   "L": 43.3,
   "D": 37.4,
   "Y": 39.3,
   "W": 47.7,
   "X": 28.7,
   "O": 54.9
  }
 },
 "maxBuild": {
  "load": [
   "lance",
   "hoar",
   "spike",
   "mantle"
  ],
  "pass": "blizzard"
 },
 "uptime": {
  "blizzard": {
   "pass": "blizzard",
   "games": 1650,
   "winrate": 46,
   "flowUptimePct": 6.5,
   "avgFrostZones": 0.38,
   "zoneUptimePct": {
    "atLeast1": 35.6,
    "atLeast2": 2.5,
    "atLeast3": 0
   }
  },
  "permafrost": {
   "pass": "permafrost",
   "games": 1650,
   "winrate": 43.2,
   "flowUptimePct": 0,
   "avgFrostZones": 1.02,
   "zoneUptimePct": {
    "atLeast1": 68.2,
    "atLeast2": 29.2,
    "atLeast3": 4.2
   }
  }
 }
}